shapesqr/__init__.py
shapesqr/abc_shapesqr.py
shapesqr/circle_shape.py
shapesqr/shape_fabric.py
shapesqr/triangle_shape.py
shapesqr-0.0.3.dist-info/METADATA
shapesqr-0.0.3.dist-info/WHEEL
shapesqr-0.0.3.dist-info/licenses/LICENSE
shapesqr-0.0.3.dist-info/RECORD
