Metadata-Version: 2.4
Name: shapesqr
Version: 0.0.3
Summary: This is a test task module for shapes square calculation.
Project-URL: Homepage, https://github.com/DmitriyReztsov/shapesqr
Project-URL: Issues, https://github.com/DmitriyReztsov/shapesqr/issues
Author-email: Dmitriy Reztsov <rezcov_d@mail.ru>
License-Expression: MIT
License-File: LICENSE
Classifier: Operating System :: OS Independent
Classifier: Programming Language :: Python :: 3
Requires-Python: >=3.10
Requires-Dist: typing-extensions==4.13.2
